comfyui_fluxflow/__init__.py
comfyui_fluxflow/model_inspector.py
comfyui_fluxflow/schedulers.py
comfyui_fluxflow/standalone_schedulers.py
comfyui_fluxflow/nodes/__init__.py
comfyui_fluxflow/nodes/latent_ops.py
comfyui_fluxflow/nodes/model_loader.py
comfyui_fluxflow/nodes/samplers.py
comfyui_fluxflow/nodes/text_encode.py
comfyui_fluxflow/nodes/utils.py
comfyui_fluxflow/web/fluxflow_types.js
fluxflow_comfyui-0.1.1.dist-info/licenses/LICENSE
fluxflow_comfyui-0.1.1.dist-info/METADATA
fluxflow_comfyui-0.1.1.dist-info/WHEEL
fluxflow_comfyui-0.1.1.dist-info/top_level.txt
fluxflow_comfyui-0.1.1.dist-info/RECORD
