Metadata-Version: 2.4
Name: fluxflow-comfyui
Version: 0.1.1
Summary: ComfyUI custom nodes for FluxFlow text-to-image generation
Author: Daniele Camisani
License: MIT
Project-URL: Homepage, https://github.com/danny-mio/fluxflow-comfyui
Project-URL: Repository, https://github.com/danny-mio/fluxflow-comfyui
Project-URL: Documentation, https://github.com/danny-mio/fluxflow-comfyui/tree/main/comfyui_fluxflow
Project-URL: Issues, https://github.com/danny-mio/fluxflow-comfyui/issues
Keywords: deep-learning,text-to-image,comfyui,diffusion,custom-nodes
Classifier: Development Status :: 4 - Beta
Classifier: Intended Audience :: Developers
Classifier: Intended Audience :: Science/Research
Classifier: License :: OSI Approved :: MIT License
Classifier: Programming Language :: Python :: 3
Classifier: Programming Language :: Python :: 3.10
Classifier: Programming Language :: Python :: 3.11
Classifier: Programming Language :: Python :: 3.12
Classifier: Topic :: Scientific/Engineering :: Artificial Intelligence
Classifier: Topic :: Multimedia :: Graphics
Requires-Python: >=3.10
License-File: LICENSE
Requires-Dist: fluxflow>=0.1.0
Requires-Dist: torch>=2.0.0
Requires-Dist: torchvision>=0.15.0
Requires-Dist: transformers>=4.30.0
Requires-Dist: pillow>=9.0.0
Requires-Dist: numpy<2.0,>=1.24.0
Provides-Extra: dev
Requires-Dist: pytest>=7.4.0; extra == "dev"
Requires-Dist: pytest-cov>=4.1.0; extra == "dev"
Requires-Dist: pytest-timeout>=2.1.0; extra == "dev"
Requires-Dist: pytest-mock>=3.11.0; extra == "dev"
Requires-Dist: black>=23.0.0; extra == "dev"
Requires-Dist: flake8>=6.0.0; extra == "dev"
Requires-Dist: isort>=5.12.0; extra == "dev"
Requires-Dist: mypy>=1.4.0; extra == "dev"
Requires-Dist: ruff>=0.1.0; extra == "dev"
Dynamic: license-file
